blocket_api/__init__.py
blocket_api/ad_parser.py
blocket_api/blocket.py
blocket_api/constants.py
blocket_api-0.4.3.dist-info/licenses/LICENSE
blocket_api-0.4.3.dist-info/METADATA
blocket_api-0.4.3.dist-info/WHEEL
blocket_api-0.4.3.dist-info/top_level.txt
blocket_api-0.4.3.dist-info/RECORD
