Metadata-Version: 2.4
Name: blocket_api
Version: 0.4.3
Summary: A python API wrapper for blocket.se
Author-email: dunderrrrrr <emil.bjorkroth@gmail.com>
Requires-Python: >=3.10
License-File: LICENSE
Requires-Dist: httpx>=0.28.1
Requires-Dist: pre-commit>=3.7.1
Requires-Dist: pytest>=8.2.2
Requires-Dist: respx>=0.21.1
Requires-Dist: mypy>=1.15.0
Requires-Dist: pydantic>=2.11.7
Requires-Dist: mkdocs>=1.6.1
Requires-Dist: mkdocs-material>=9.6.21
Requires-Dist: mkdocs-swagger-ui-tag>=0.7.2
Requires-Dist: beautifulsoup4>=4.14.2
Requires-Dist: ruff>=0.14.10
Dynamic: license-file
